akasha/__init__.py
akasha/client.py
akasha/constants.py
akasha/enums.py
akasha/errors.py
akasha/models/__init__.py
akasha/models/artifact.py
akasha/models/category.py
akasha/models/leaderboard.py
akasha/models/profile.py
akasha/models/user_calc.py
akasha/paginators/leaderboard.py
akasha/paginators/profile.py
akasha_py-0.3.0.dist-info/WHEEL
akasha_py-0.3.0.dist-info/METADATA
akasha_py-0.3.0.dist-info/RECORD
