Metadata-Version: 2.3
Name: akasha-py
Version: 0.3.0
Summary: Async API wrapper for akasha.cv written in Python
Author: seriaati
Author-email: seriaati <seria.ati@gmail.com>
License: GNU GENERAL PUBLIC LICENSE
Requires-Dist: aiohttp>=3.10.5
Requires-Dist: aiohttp-client-cache[sqlite]>=0.11.1
Requires-Dist: loguru>=0.7.2
Requires-Dist: pydantic>=2.9.2
Requires-Python: >=3.11
Project-URL: Homepage, https://github.com/seriaati/akasha-py
Project-URL: Issues, https://github.com/seriaati/akasha-py/issues
Project-URL: Repository, https://github.com/seriaati/akasha-py.git
